src/__init__.py
src/cli.py
src/cli_dispatch.py
src/cli_help.py
src/tui.py
src/common/__init__.py
src/common/b2.py
src/common/banner.py
src/common/capsule.py
src/common/cas.py
src/common/config.py
src/common/console.py
src/common/credentials.py
src/common/detective.py
src/common/hashing.py
src/common/hooks.py
src/common/ignore.py
src/common/logger.py
src/common/manifest.py
src/common/notifications.py
src/common/paths.py
src/common/s3.py
src/common/smart_init.py
src/projectclone/__init__.py
src/projectclone/backup.py
src/projectclone/banner.py
src/projectclone/cas_engine.py
src/projectclone/checkout_engine.py
src/projectclone/cleanup.py
src/projectclone/cli.py
src/projectclone/diff_engine.py
src/projectclone/gc_engine.py
src/projectclone/integrity_engine.py
src/projectclone/list_engine.py
src/projectclone/rotation.py
src/projectclone/scanner.py
src/projectclone/status_engine.py
src/projectclone/sync_engine.py
src/projectclone/utils.py
src/projectclone/verify_engine.py
src/projectclone/tests/test_backup.py
src/projectclone/tests/test_backup_coverage.py
src/projectclone/tests/test_backup_coverage_gaps.py
src/projectclone/tests/test_backup_exclude_param.py
src/projectclone/tests/test_backup_exclude_symlinks.py
src/projectclone/tests/test_backup_ext.py
src/projectclone/tests/test_backup_extended.py
src/projectclone/tests/test_backup_log_coverage.py
src/projectclone/tests/test_backup_more_logs.py
src/projectclone/tests/test_backup_summary.py
src/projectclone/tests/test_backup_ultra.py
src/projectclone/tests/test_banner.py
src/projectclone/tests/test_cas_engine.py
src/projectclone/tests/test_cas_symlinks.py
src/projectclone/tests/test_checkout_coverage.py
src/projectclone/tests/test_cleanup.py
src/projectclone/tests/test_cleanup_extended.py
src/projectclone/tests/test_cleanup_verbose.py
src/projectclone/tests/test_cli_coverage.py
src/projectclone/tests/test_cli_ext.py
src/projectclone/tests/test_cli_ext_v2.py
src/projectclone/tests/test_cli_extended.py
project_vault-11.0.0.dist-info/METADATA
project_vault-11.0.0.dist-info/WHEEL
project_vault-11.0.0.dist-info/entry_points.txt
project_vault-11.0.0.dist-info/top_level.txt
project_vault-11.0.0.dist-info/RECORD
