Metadata-Version: 2.4
Name: project-vault
Version: 11.0.0
Summary: The Unified Project Lifecycle Manager: Backup, Restore, and Teleport Projects Anywhere.
Author-email: Dhruv <your.email@example.com>
License: MIT
Requires-Python: >=3.10
Requires-Dist: boto3
Requires-Dist: b2sdk
Requires-Dist: rich
Requires-Dist: zstandard>=0.22.0
Requires-Dist: textual>=0.50.0
Requires-Dist: tomli; python_version < "3.11"
Provides-Extra: dev
Requires-Dist: pytest>=8.0.0; extra == "dev"
Requires-Dist: pytest-cov>=5.0.0; extra == "dev"
Requires-Dist: pytest-timeout>=2.2.0; extra == "dev"
Requires-Dist: pytest-json-report>=1.5.0; extra == "dev"
Requires-Dist: pytest-asyncio>=0.23.0; extra == "dev"
Requires-Dist: pytest-mock>=3.10.0; extra == "dev"
Requires-Dist: pyfakefs>=5.0.0; extra == "dev"
Requires-Dist: ruff>=0.6.0; extra == "dev"
Requires-Dist: black>=24.3.0; extra == "dev"
Requires-Dist: mypy>=1.11.0; extra == "dev"
Requires-Dist: PyYAML>=6.0; extra == "dev"
Requires-Dist: types-PyYAML>=6.0; extra == "dev"
